pegasus/__init__.py
pegasus/__main__.py
pegasus/annotate_cluster/__init__.py
pegasus/annotate_cluster/annotate_cluster.py
pegasus/annotate_cluster/human_brain_cell_markers.json
pegasus/annotate_cluster/human_immune_cell_markers.json
pegasus/annotate_cluster/human_lung_cell_markers.json
pegasus/annotate_cluster/mouse_brain_cell_markers.json
pegasus/annotate_cluster/mouse_immune_cell_markers.json
pegasus/annotate_cluster/mouse_liver_cell_markers.json
pegasus/annotate_cluster/mouse_lung_cell_markers.json
pegasus/check_sample_indexes/Chromium-i7-Multiplex-Kit-N-Set-A-sample-indexes-plate.json
pegasus/check_sample_indexes/__init__.py
pegasus/check_sample_indexes/check_sample_indexes.py
pegasus/check_sample_indexes/chromium-shared-sample-indexes-plate.json
pegasus/commands/AnnotateCluster.py
pegasus/commands/Base.py
pegasus/commands/CheckSampleIndexes.py
pegasus/commands/Clustering.py
pegasus/commands/DeAnalysis.py
pegasus/commands/FindMarkers.py
pegasus/commands/Plotting.py
pegasus/commands/SCPOutput.py
pegasus/commands/SubClustering.py
pegasus/commands/View.py
pegasus/commands/__init__.py
pegasus/cylib/cfisher.cpython-39-darwin.so
pegasus/cylib/de_utils.cpython-39-darwin.so
pegasus/cylib/fast_utils.cpython-39-darwin.so
pegasus/data_files/apoptosis_human.gmt
pegasus/data_files/apoptosis_mouse.gmt
pegasus/data_files/c2.cp.v7.5.1.symbols.gmt
pegasus/data_files/cell_cycle_human.gmt
pegasus/data_files/cell_cycle_mouse.gmt
pegasus/data_files/emt_human.gmt
pegasus/data_files/gender_human.gmt
pegasus/data_files/gender_mouse.gmt
pegasus/data_files/h.all.v7.5.1.symbols.gmt
pegasus/data_files/human_lung.gmt
pegasus/data_files/human_t_cell_markers.gmt
pegasus/data_files/mitochondrial_genes_human.gmt
pegasus/data_files/mitochondrial_genes_mouse.gmt
pegasus/data_files/mouse_brain.gmt
pegasus/data_files/mouse_liver.gmt
pegasus/data_files/mouse_lung.gmt
pegasus/data_files/ribosomal_genes_human.gmt
pegasus/data_files/ribosomal_genes_mouse.gmt
pegasus/data_files/tonsil_markers.gmt
pegasuspy-1.10.2.dist-info/LICENSE
pegasuspy-1.10.2.dist-info/METADATA
pegasuspy-1.10.2.dist-info/WHEEL
pegasuspy-1.10.2.dist-info/entry_points.txt
pegasuspy-1.10.2.dist-info/top_level.txt
pegasuspy-1.10.2.dist-info/RECORD
